cut_sent_thai/__init__.py
cut_sent_thai/cut_sent_utils.py
cut_sent_thai/cut_sentence.h5
cut_sent_thai/cut_sentence.pt
cut_sent_thai/inference_cut_sentence_before_pack.py
cut_sent_thai/main.py
cut_sent_thai/stoi.pickle
cut_sent_thai/stoi_pos.pickle
cut_sent_thai/train_cut_sentence_orchid.py
cut_sent_thai/train_cut_sentence_orchid_pt.py
cut_sent_thai/train_sent_tok_perfect_word_tok.py
cut_sent_thai-0.1.0.dist-info/LICENSE.txt
cut_sent_thai-0.1.0.dist-info/METADATA
cut_sent_thai-0.1.0.dist-info/WHEEL
cut_sent_thai-0.1.0.dist-info/top_level.txt
cut_sent_thai-0.1.0.dist-info/RECORD
