Metadata-Version: 2.1
Name: cut-sent-thai
Version: 0.1.0
Summary: tokenize sentence in Thai
Home-page: UNKNOWN
Author: sumeth
Author-email: author@example.com
License: MIT
Platform: UNKNOWN
Requires-Python: >=3.6
Requires-Dist: numpy
Requires-Dist: tensorflow (>=2.2.0)
Requires-Dist: pythainlp (>=2.2.0)
Requires-Dist: ujson
